evalsafe/__init__.py
EvalSafe-1.dist-info/METADATA
EvalSafe-1.dist-info/WHEEL
EvalSafe-1.dist-info/top_level.txt
EvalSafe-1.dist-info/RECORD
