Metadata-Version: 2.1
Name: EvalSafe
Version: 1
Summary: Calculate expressions in a string using eval without security threats!
Home-page: https://github.com/Zedikon/EvalSafe
Author: Zedikon
Author-email: mrzedikon@gmail.com
License: UNKNOWN
Platform: UNKNOWN
Classifier: Programming Language :: Python :: 3.10
Classifier: License :: OSI Approved :: GNU General Public License v3 (GPLv3)
